fits2image/__init__.py
fits2image/conversions.py
fits2image/scaling.py
fits2image-0.4.11.dist-info/licenses/LICENSE
fits2image-0.4.11.dist-info/METADATA
fits2image-0.4.11.dist-info/WHEEL
fits2image-0.4.11.dist-info/top_level.txt
fits2image-0.4.11.dist-info/RECORD
