Metadata-Version: 2.4
Name: fits2image
Version: 0.4.11
Summary: Common libraries for the conversion and scaling of fits images
Author: Jon Nation
Author-email: jnation@lcogt.net
License-File: LICENSE
Requires-Dist: numpy
Requires-Dist: astropy
Requires-Dist: Pillow
Dynamic: author
Dynamic: author-email
Dynamic: description
Dynamic: license-file
Dynamic: requires-dist
Dynamic: summary
